bmrs.py
bmrs-2021.7.4.dist-info/LICENSE
bmrs-2021.7.4.dist-info/WHEEL
bmrs-2021.7.4.dist-info/METADATA
bmrs-2021.7.4.dist-info/RECORD
