Metadata-Version: 2.1
Name: bmrs
Version: 2021.7.4
Summary: This package enables you receive BMRS data as json instead of the default XML
Home-page: https://github.com/SimiCode/bmrs-json-api
Author: Edison Abahurire
Author-email: abahedison@gmail.com
Requires-Python: >=3.6
Classifier: Intended Audience :: Developers
Classifier: License :: OSI Approved :: MIT License
Classifier: Programming Language :: Python :: 3
Classifier: Topic :: Software Development :: Libraries :: Python Modules
Requires-Dist: docopt >=0.6.2
Requires-Dist: stomp.py >=4.1.22
Requires-Dist: xmltodict >=0.12.0
